alu_4_bit.v
module alu_4_bit(A,B,clk,rst,mode,y);

	input wire [3:0]A,B;
	input clk,rst;
	output reg [7:0]y;
        input[2:0]mode;

    	always@(posedge clk)begin
	   	
        if(rst) begin

	    y<= 8'b0000_0000;
        end
	   // else begin
		case(mode)
           3'b000: y<= A+B;
     	   3'b001: y<= A-B;
	   3'b010: y<= A*B;
	   3'b011: y<= A/B;
	   3'b100: y<= A & B;
	   3'b101: y<= A | B;
 	   3'b110: y<= A ^ B;
	   3'b111: y<= ~A;
           default:y<= 8'b0000_0000;
       endcase
     //  end
      
   end 
endmodule

tb_alu_4_bit.v
`timescale 1ns/1ps
module tb_alu_4_bit;

  reg[3:0] A,B;
  reg clk,rst;
  reg [2:0]mode;
  wire[7:0]y;
  alu_4_bit uut(
	  .A(A),
          .B(B),
	  .mode(mode),
	  .y(y),
           .clk(clk),
	   .rst(rst)
   );

   always #5 clk=~clk;
   initial begin
             rst=1; A=0; B=0; mode=0; clk=0;

	   #10 rst=0; 

         /*repeat(15) begin
	     #20; 
             A=$random;
             B=$random;
	     mode=$random;
         end
         */ 
	 #30; mode = 3'b000; A = 4'b1010; B = 4'b1000; // ADD   18  carry generate 
	 #30; mode = 3'b001; A = 4'b1010; B = 4'b0010; // SUB   08
         #30; mode = 3'b010; A = 4'b1010; B = 4'b0010; // MUL   20
	 #30; mode = 3'b011; A = 4'b1010; B = 4'b0010; // Div   05
         #30; mode = 3'b100; A = 4'b1010; B = 4'b0010; // AND  0000_0010
	 #30; mode = 3'b101; A = 4'b1011; B = 4'b0010; // OR   0000_1011
         #30; mode = 3'b110; A = 4'b1110; B = 4'b0101; // MUL   70
	 #30; mode = 3'b111; A = 4'b1100; B = 4'b0011; // NOT A  00000_0101
	 #30; mode = 3'b101; A = 4'b1111; B = 4'b0011; // OR     0000_1111   
	 #30; mode = 3'b001; A = 4'b0101; B = 4'b1111; // SUB    -10  => 0001_0110  borrow is generated   
	 #30; mode = 3'b011; A = 4'b1010; B = 4'b0010; //Div
	 #30; mode = 3'b111; A = 4'b1100; B = 4'b0011; //NOT A   0000_1111 carry not generated 
 
      end

   // end

 initial begin 
     $dumpfile("tb_alu_4_bit.vcd");
     $dumpvars(0,tb_alu_4_bit);
    #400;
  $finish;
end
endmodule

tb_alu_4_bit.vcd
$date
	Sat Feb  3 00:05:59 2024
$end
$version
	Icarus Verilog
$end
$timescale
	1ps
$end
$scope module tb_alu_4_bit $end
$var wire 8 ! y [7:0] $end
$var reg 4 " A [3:0] $end
$var reg 4 # B [3:0] $end
$var reg 1 $ clk $end
$var reg 3 % mode [2:0] $end
$var reg 1 & rst $end
$scope module uut $end
$var wire 4 ' A [3:0] $end
$var wire 4 ( B [3:0] $end
$var wire 1 $ clk $end
$var wire 3 ) mode [2:0] $end
$var wire 1 & rst $end
$var reg 8 * y [7:0] $end
$upscope $end
$upscope $end
$enddefinitions $end
#0
$dumpvars
bx *
b0 )
b0 (
b0 '
1&
b0 %
0$
b0 #
b0 "
bx !
$end
#5000
b0 !
b0 *
1$
#10000
0$
0&
#15000
1$
#20000
0$
#25000
1$
#30000
0$
#35000
1$
#40000
0$
b1000 #
b1000 (
b1010 "
b1010 '
#45000
b10010 !
b10010 *
1$
#50000
0$
#55000
1$
#60000
0$
#65000
1$
#70000
0$
b10 #
b10 (
b1 %
b1 )
#75000
b1000 !
b1000 *
1$
#80000
0$
#85000
1$
#90000
0$
#95000
1$
#100000
0$
b10 %
b10 )
#105000
b10100 !
b10100 *
1$
#110000
0$
#115000
1$
#120000
0$
#125000
1$
#130000
0$
b11 %
b11 )
#135000
b101 !
b101 *
1$
#140000
0$
#145000
1$
#150000
0$
#155000
1$
#160000
0$
b100 %
b100 )
#165000
b10 !
b10 *
1$
#170000
0$
#175000
1$
#180000
0$
#185000
1$
#190000
0$
b1011 "
b1011 '
b101 %
b101 )
#195000
b1011 !
b1011 *
1$
#200000
0$
#205000
1$
#210000
0$
#215000
1$
#220000
0$
b101 #
b101 (
b1110 "
b1110 '
b110 %
b110 )
#225000
1$
#230000
0$
#235000
1$
#240000
0$
#245000
1$
#250000
0$
b11 #
b11 (
b1100 "
b1100 '
b111 %
b111 )
#255000
b11110011 !
b11110011 *
1$
#260000
0$
#265000
1$
#270000
0$
#275000
1$
#280000
0$
b1111 "
b1111 '
b101 %
b101 )
#285000
b1111 !
b1111 *
1$
#290000
0$
#295000
1$
#300000
0$
#305000
1$
#310000
0$
b1111 #
b1111 (
b101 "
b101 '
b1 %
b1 )
#315000
b11110110 !
b11110110 *
1$
#320000
0$
#325000
1$
#330000
0$
#335000
1$
#340000
0$
b10 #
b10 (
b1010 "
b1010 '
b11 %
b11 )
#345000
b101 !
b101 *
1$
#350000
0$
#355000
1$
#360000
0$
#365000
1$
#370000
0$
b11 #
b11 (
b1100 "
b1100 '
b111 %
b111 )
#375000
b11110011 !
b11110011 *
1$
